repliclust/__init__.py
repliclust/base.py
repliclust/config.py
repliclust/distortion.py
repliclust/distributions.py
repliclust/natural_language.py
repliclust/random_centers.py
repliclust/utils.py
repliclust/viz.py
repliclust/maxmin/__init__.py
repliclust/maxmin/archetype.py
repliclust/maxmin/covariance.py
repliclust/maxmin/groupsizes.py
repliclust/maxmin/utils.py
repliclust/overlap/__init__.py
repliclust/overlap/_gradients.py
repliclust/overlap/centers.py
repliclust-1.0.0.dist-info/METADATA
repliclust-1.0.0.dist-info/WHEEL
repliclust-1.0.0.dist-info/licenses/LICENSE.txt
repliclust-1.0.0.dist-info/RECORD
