Metadata-Version: 2.3
Name: repliclust
Version: 1.0.0
Summary: Generate synthetic data with clusters.
Project-URL: Homepage, https://repliclust.org
Project-URL: Source, https://github.com/mzelling/repliclust
Project-URL: Bug Tracker, https://github.com/mzelling/repliclust/issues
Author-email: Mike Zellinger <mike.j.zellinger@gmail.com>
License-File: LICENSE.txt
Classifier: License :: OSI Approved :: BSD License
Classifier: Operating System :: OS Independent
Classifier: Programming Language :: Python :: 3
Requires-Python: >=3.9
Requires-Dist: matplotlib
Requires-Dist: numpy
Requires-Dist: openai
Requires-Dist: python-dotenv
Requires-Dist: scikit-learn
Requires-Dist: scipy
Requires-Dist: threadpoolctl
Requires-Dist: torch
Requires-Dist: tqdm
Requires-Dist: umap-learn
